frameless_dialog/__init__.py
frameless_dialog/frmls_dialog.py
frameless_dialog/frmls_msgbx.py
frameless_dialog/frmls_resources.py
frameless_dialog-0.2.0.dist-info/LICENSE.txt
frameless_dialog-0.2.0.dist-info/METADATA
frameless_dialog-0.2.0.dist-info/WHEEL
frameless_dialog-0.2.0.dist-info/top_level.txt
frameless_dialog-0.2.0.dist-info/RECORD
