Metadata-Version: 2.1
Name: frameless_dialog
Version: 0.2.0
Summary: A frameless QDialog widget
Home-page: https://github.com/philip-messner/Frameless_Dialog/
Author: Philip Messner
Author-email: rxphil35@gmail.com
License: MIT
Platform: Windows
Classifier: Development Status :: 4 - Beta
Classifier: Programming Language :: Python
License-File: LICENSE.txt
Requires-Dist: importlib-metadata
Requires-Dist: PyQt6
Provides-Extra: testing
Requires-Dist: setuptools ; extra == 'testing'
Requires-Dist: pytest ; extra == 'testing'
Requires-Dist: pytest-cov ; extra == 'testing'
